README.md
setup.py
marathon_deploy/__init__.py
marathon_deploy/checkappdeploy.py
marathon_deploy/deploytool.py
marathon_deploy/version.py
marathon_deploy.egg-info/PKG-INFO
marathon_deploy.egg-info/SOURCES.txt
marathon_deploy.egg-info/dependency_links.txt
marathon_deploy.egg-info/entry_points.txt
marathon_deploy.egg-info/not-zip-safe
marathon_deploy.egg-info/requires.txt
marathon_deploy.egg-info/top_level.txt
marathon_deploy/utils/__init__.py
marathon_deploy/utils/actions.py
marathon_deploy/utils/common.py
marathon_deploy/utils/events.py
marathon_deploy/utils/string_mangling.py