Metadata-Version: 1.0
Name: marathon-deploy
Version: 3.0.2
Summary: CLI tool to manage deployment of applications to Marathon from JSON files
Home-page: UNKNOWN
Author: Nicolas Villanueva
Author-email: villanueva.arg@gmail.com
License: UNKNOWN
Platform: UNKNOWN
